pyDWS/__init__.py
pyDWS/data_preprocessing.py
pyDWS/icf_fit.py
pyDWS/microrheology.py
pyDWS/msd.py
pyDWS/plots.py
pyDWS/plottingStyle.mplstyle
pyDWS/tc_echo_merge.py
pyDWS/utils.py
pydws-1.1.1.dist-info/licenses/LICENSE
pydws-1.1.1.dist-info/METADATA
pydws-1.1.1.dist-info/WHEEL
pydws-1.1.1.dist-info/top_level.txt
pydws-1.1.1.dist-info/RECORD
