Metadata-Version: 2.4
Name: pyDWS
Version: 1.1.1
Summary: A Python package for the analysis of Diffusing Wave Spectroscopy and tracer bead microrheology data.
Author-email: "M. Helfer, C. Zhang, and F. Scheffold" <frank.scheffold@unifr.ch>
License: MIT
Project-URL: Homepage, https://github.com/ManuelH26/pyDWS
Project-URL: Bug Tracker, https://github.com/ManuelH26/pyDWS/issues
Project-URL: Source Code, https://github.com/ManuelH26/pyDWS
Requires-Python: >=3.10
License-File: LICENSE
Requires-Dist: numpy>=1.21.0
Requires-Dist: matplotlib>=3.4.3
Requires-Dist: pandas>=1.3.0
Requires-Dist: scikit_learn>=1.0.0
Requires-Dist: scipy>=1.7.0
Requires-Dist: statsmodels>=0.14.5
Provides-Extra: dev
Requires-Dist: jupyter; extra == "dev"
Dynamic: license-file
